pybmx-0.2.2.dist-info/METADATA
pybmx-0.2.2.dist-info/WHEEL
pybmx-0.2.2.dist-info/entry_points.txt
pybmx-0.2.2.dist-info/licenses/LICENSE
pybmx/__init__.py
pybmx/bme.py
pybmx/calibration.py
pybmx/configuration.py
pybmx/enums.py
pybmx/errors.py
pybmx/io.py
pybmx/types.py
pybmx/utils.py
pybmx-0.2.2.dist-info/RECORD
