Metadata-Version: 2.4
Name: pybmx
Version: 0.2.2
Summary: Bosch sensor BMP and BME library
Author-Email: Nico Hanisch <donsprallo@gmail.com>
License-Expression: MIT
Classifier: Development Status :: 3 - Alpha
Classifier: Programming Language :: Python :: 3
Classifier: Programming Language :: Python :: 3.10
Classifier: Programming Language :: Python :: 3.11
Classifier: Programming Language :: Python :: 3.12
Classifier: Programming Language :: Python :: 3.13
Project-URL: Homepage, https://github.com/donsprallo/pybmx
Requires-Python: >=3.10
Requires-Dist: smbus2>=0.5.0
Requires-Dist: loguru>=0.7.3
